spannermockserver/__init__.py
spannermockserver/mock_database_admin.py
spannermockserver/mock_spanner.py
spannermockserver/generated/__init__.py
spannermockserver/generated/spanner_database_admin_pb2_grpc.py
spannermockserver/generated/spanner_pb2_grpc.py
spannermockserver/testbase/__init__.py
spannermockserver/testbase/mock_server_test_base.py
spannermockserver-0.1.2.dist-info/licenses/LICENSE
spannermockserver-0.1.2.dist-info/METADATA
spannermockserver-0.1.2.dist-info/WHEEL
spannermockserver-0.1.2.dist-info/top_level.txt
spannermockserver-0.1.2.dist-info/RECORD
